client/__init__.py
client/client.py
client/client/__init__.py
client/client/client_db.py
client/client/qt/__init__.py
client/client/qt/login_dialog.py
client/client/qt/main_window.py
client/common/__init__.py
client/common/descriptors.py
client/common/meta.py
client/common/settings.py
client/common/tcp_socket.py
client/logs/__init__.py
client/logs/logfiles/__init__.py
client/logs/settings/__init__.py
client/logs/settings/colored_formatter.py
client/logs/settings/log_decorator.py
client/logs/settings/socket_logger.py
qt_messenger_client-0.0.3.dist-info/METADATA
qt_messenger_client-0.0.3.dist-info/WHEEL
qt_messenger_client-0.0.3.dist-info/top_level.txt
qt_messenger_client-0.0.3.dist-info/RECORD
